chipiq/__init__.py
chipiq/__main__.py
chipiq/simiq/__init__.py
chipiq/simiq/simiq.py
chipiq-0.0.4.dist-info/METADATA
chipiq-0.0.4.dist-info/WHEEL
chipiq-0.0.4.dist-info/entry_points.txt
chipiq-0.0.4.dist-info/RECORD
