Metadata-Version: 2.4
Name: chipiq
Version: 0.0.4
Summary: ChipIQ - Intelligent EDA AI-Agents for Chip Design
Project-URL: Documentation, https://github.com/ChipIQ/chipiq#readme
Project-URL: Issues, https://github.com/ChipIQ/chipiq/issues
Project-URL: Source, https://github.com/ChipIQ/chipiq
Author-email: Hans Bouwmeester <hans.bouwmeester@icloud.com>, Asav Gandhi <asavgandhi01@gmail.com>
Classifier: Operating System :: OS Independent
Classifier: Programming Language :: Python
Classifier: Programming Language :: Python :: 3.13
Requires-Python: >=3.13
Requires-Dist: pydantic>=2.12.4
